{
  "Rows": {
    "RowColumnAttachedInfos": {
      "1": {
        "GridRowColumnDefinition": {
          "DesignLengthInPixel": 25.0
        }
      }
    },
    "Count": 2,
    "DefaultSize": 25.0
  },
  "Cols": {
    "RowColumnAttachedInfos": {
      "2": {
        "GridRowColumnDefinition": {
          "DesignLengthInPixel": 20.0
        }
      },
      "31": {
        "GridRowColumnDefinition": {
          "DesignLengthInPixel": 10.0
        }
      },
      "32": {
        "GridRowColumnDefinition": {
          "DesignLengthInPixel": 10.0
        }
      },
      "33": {
        "GridRowColumnDefinition": {
          "DesignLengthInPixel": 10.0
        }
      },
      "34": {
        "GridRowColumnDefinition": {
          "DesignLengthInPixel": 10.0
        }
      },
      "35": {
        "GridRowColumnDefinition": {
          "DesignLengthInPixel": 10.0
        }
      },
      "36": {
        "GridRowColumnDefinition": {
          "DesignLengthInPixel": 10.0
        }
      },
      "37": {
        "GridRowColumnDefinition": {
          "DesignLengthInPixel": 10.0
        }
      },
      "38": {
        "GridRowColumnDefinition": {
          "DesignLengthInPixel": 10.0
        }
      },
      "39": {
        "GridRowColumnDefinition": {
          "DesignLengthInPixel": 10.0
        }
      },
      "40": {
        "GridRowColumnDefinition": {
          "DesignLengthInPixel": 10.0
        }
      },
      "41": {
        "GridRowColumnDefinition": {
          "DesignLengthInPixel": 10.0
        }
      },
      "42": {
        "GridRowColumnDefinition": {
          "DesignLengthInPixel": 10.0
        }
      },
      "43": {
        "GridRowColumnDefinition": {
          "DesignLengthInPixel": 10.0
        }
      },
      "44": {
        "GridRowColumnDefinition": {
          "DesignLengthInPixel": 10.0
        }
      },
      "45": {
        "GridRowColumnDefinition": {
          "DesignLengthInPixel": 10.0
        }
      },
      "46": {
        "GridRowColumnDefinition": {
          "DesignLengthInPixel": 10.0
        }
      },
      "47": {
        "GridRowColumnDefinition": {
          "DesignLengthInPixel": 20.0,
          "IsHidden": true
        }
      },
      "54": {
        "GridRowColumnDefinition": {
          "DesignLengthInPixel": 20.0,
          "IsHidden": true
        }
      },
      "55": {
        "GridRowColumnDefinition": {
          "DesignLengthInPixel": 20.0,
          "IsHidden": true
        }
      }
    },
    "InLogicalVisibleIndexes": [
      47,
      48,
      49,
      50,
      51,
      52,
      53,
      54,
      55
    ],
    "Count": 56
  },
  "Values": {
    "0,34": "",
    "0,37": "",
    "0,40": "",
    "0,43": "",
    "0,48": "▼添付ID",
    "0,51": "▼添付コメント数"
  },
  "AttachInfos": {
    "0,0": {
      "CellType": {
        "$type": "Forguncy.CheckBoxCellType, ServerDesignerCommon",
        "Style": 1,
        "PrimaryColor": "#FF005B47"
      },
      "TemplateCellSource": "選択"
    },
    "0,2": {
      "ConditionFormatRulesCollection": {
        "Rules": [
          {
            "$type": "Forguncy.ConditionFormat.FormulaRule, ServerDesignerCommon",
            "Formula": {
              "$type": "Forguncy.Model.FormulaReferObject, ServerDesignerCommon",
              "SerializeProperty": "='74995f23fcce42ecba69efcc8a3414e'!$A$1"
            },
            "StyleInfo": {
              "FontWeight": "Bold",
              "Underline": null,
              "Strikethrough": null
            }
          }
        ]
      },
      "TemplateCellSource": "ファイル名"
    },
    "0,24": {
      "TemplateCellSource": "所属会社名"
    },
    "0,31": {
      "CellType": {
        "$type": "Forguncy.ImageCellType, ServerDesignerCommon",
        "CommandList": [
          {
            "$type": "Forguncy.Model.SetCellPropertyCommand, ServerDesignerCommon",
            "PropertyItemsList": [
              {
                "TargetCells": {
                  "$type": "Forguncy.Model.FormulaReferObject, ServerDesignerCommon",
                  "SerializeProperty": "='74995f23fcce42ecba69efcc8a3414e'!選択中添付ID"
                },
                "Value": {
                  "$type": "Forguncy.Model.FormulaReferObject, ServerDesignerCommon",
                  "SerializeProperty": "='74995f23fcce42ecba69efcc8a3414e'!AW2"
                }
              },
              {
                "TargetCells": {
                  "$type": "Forguncy.Model.FormulaReferObject, ServerDesignerCommon",
                  "SerializeProperty": "='74995f23fcce42ecba69efcc8a3414e'!添付コメントタイトル"
                },
                "Value": {
                  "$type": "Forguncy.Model.FormulaReferObject, ServerDesignerCommon",
                  "SerializeProperty": "=\"ファイル名：\"&'74995f23fcce42ecba69efcc8a3414e'!C1&\"に対するコメント\""
                }
              }
            ]
          }
        ],
        "ToolTip": {
          "$type": "Forguncy.Model.FormulaReferObject, ServerDesignerCommon",
          "SerializeProperty": "='74995f23fcce42ecba69efcc8a3414e'!AZ2&\"件のコメントが登録されています\""
        },
        "TemplateKey": "オレンジ",
        "IsInvisible": true,
        "ImagePath": "Mobile/415_message_1.svg",
        "BuiltIn": true,
        "Color": "Accent 4 0",
        "UseCellForeColor": true
      },
      "ConditionFormatRulesCollection": {
        "Rules": [
          {
            "$type": "Forguncy.ConditionFormat.FormulaRule, ServerDesignerCommon",
            "Formula": {
              "$type": "Forguncy.Model.FormulaReferObject, ServerDesignerCommon",
              "SerializeProperty": "='74995f23fcce42ecba69efcc8a3414e'!$AZ$2>0"
            },
            "StyleInfo": {
              "Underline": null,
              "Strikethrough": null
            },
            "IsDisabled": false,
            "IsInvisible": false,
            "IsReadOnly": false
          }
        ]
      }
    },
    "0,34": {
      "CellType": {
        "$type": "Forguncy.ImageCellType, ServerDesignerCommon",
        "CommandList": [
          {
            "$type": "Forguncy.Model.ShowPopupCommand, ServerDesignerCommon",
            "PageName": "添付コメント登録",
            "PassValues": [
              {
                "Source": {
                  "$type": "Forguncy.Model.FormulaReferObject, ServerDesignerCommon",
                  "SerializeProperty": "='74995f23fcce42ecba69efcc8a3414e'!AW2"
                },
                "TargetCell": {
                  "SerializeProperty": "=添付コメント登録!AB5"
                }
              },
              {
                "Source": {
                  "$type": "Forguncy.Model.FormulaReferObject, ServerDesignerCommon",
                  "SerializeProperty": "='74995f23fcce42ecba69efcc8a3414e'!C1"
                },
                "TargetCell": {
                  "SerializeProperty": "=添付コメント登録!対象ファイル名"
                }
              }
            ],
            "LoadBindingDataOption": 2
          }
        ],
        "ToolTip": "コメントを追加します",
        "TemplateKey": "リスト用",
        "ImagePath": "Application/028_edit_8.svg",
        "BuiltIn": true,
        "Color": "Background 1 -35",
        "UseCellForeColor": true
      }
    },
    "0,37": {
      "CellType": {
        "$type": "Forguncy.ImageCellType, ServerDesignerCommon",
        "CommandList": [
          {
            "$type": "Forguncy.Model.RequestServerCommand, ServerDesignerCommon",
            "ServerCommandName": "ファイルダウンロード処理",
            "Parameters": [
              {
                "$type": "Forguncy.Model.RequestServerCommandObjectParam, ServerDesignerCommon",
                "Value": {
                  "$type": "Forguncy.Model.FormulaReferObject, ServerDesignerCommon",
                  "SerializeProperty": "='74995f23fcce42ecba69efcc8a3414e'!AW2"
                },
                "ParamName": "P_添付ID"
              }
            ],
            "ResultErrorCodeTo": {
              "SerializeProperty": "リターンコード"
            },
            "ResultMessageTo": {
              "SerializeProperty": "リターンメッセージ"
            },
            "CheckDataValidation": false
          },
          {
            "$type": "Forguncy.Model.ConditionCommand, ServerDesignerCommon",
            "ConditionAndCommandPairList": [
              {
                "Condition": {
                  "$type": "Forguncy.Model.IfCondition, ServerDesignerCommon",
                  "param": {
                    "$type": "Forguncy.Model.IfConditionPageElementParam, ServerDesignerCommon",
                    "cellLocations": [
                      {
                        "SerializeProperty": "='74995f23fcce42ecba69efcc8a3414e'!リターンコード"
                      }
                    ]
                  },
                  "value": "0",
                  "compareType": 1
                },
                "CommandList": [
                  {
                    "$type": "Forguncy.Model.ShowMessageCommand, ServerDesignerCommon",
                    "MessageFormula": {
                      "$type": "Forguncy.Model.FormulaReferObject, ServerDesignerCommon",
                      "SerializeProperty": "='74995f23fcce42ecba69efcc8a3414e'!リターンメッセージ"
                    }
                  }
                ],
                "ID": "53600c90-9b0d-4980-818a-71b0fd8b3138"
              }
            ]
          }
        ],
        "ToolTip": "ファイルをダウンロードします",
        "TemplateKey": "リスト用",
        "ImagePath": "Application/111_download_6.svg",
        "BuiltIn": true,
        "Color": "Background 1 -35",
        "UseCellForeColor": true
      }
    },
    "0,40": {
      "CellType": {
        "$type": "Forguncy.ImageCellType, ServerDesignerCommon",
        "CommandList": [
          {
            "$type": "Forguncy.Model.ShowPopupCommand, ServerDesignerCommon",
            "PageName": "添付ファイル編集",
            "PassValues": [],
            "LoadBindingDataOption": 1
          }
        ],
        "ToolTip": "ファイル名を編集できます",
        "TemplateKey": "リスト用",
        "ImagePath": "Application/053_settings_4.svg",
        "BuiltIn": true,
        "Color": "Background 1 -35",
        "UseCellForeColor": true
      }
    },
    "0,43": {
      "CellType": {
        "$type": "Forguncy.ImageCellType, ServerDesignerCommon",
        "CommandList": [
          {
            "$type": "Forguncy.Model.ConditionCommand, ServerDesignerCommon",
            "ConditionAndCommandPairList": [
              {
                "ConfirmDialogSettings": {
                  "Title": "確認",
                  "FormulaText": {
                    "$type": "Forguncy.Model.FormulaReferObject, ServerDesignerCommon",
                    "SerializeProperty": "=\"ファイル名：\"&'74995f23fcce42ecba69efcc8a3414e'!C1&CHAR(10)&\"このファイルを削除します。よろしいですか？\""
                  },
                  "YesButtonText": "はい",
                  "NoButtonText": "いいえ",
                  "ConfirmIcon": 4
                },
                "CommandList": [
                  {
                    "$type": "Forguncy.Model.RequestServerCommand, ServerDesignerCommon",
                    "ServerCommandName": "ファイル削除処理",
                    "Parameters": [
                      {
                        "$type": "Forguncy.Model.RequestServerCommandObjectParam, ServerDesignerCommon",
                        "Value": {
                          "$type": "Forguncy.Model.FormulaReferObject, ServerDesignerCommon",
                          "SerializeProperty": "='74995f23fcce42ecba69efcc8a3414e'!AW2"
                        },
                        "ParamName": "P_添付ID"
                      }
                    ],
                    "ResultErrorCodeTo": {
                      "SerializeProperty": "リターンコード"
                    },
                    "ResultMessageTo": {
                      "SerializeProperty": "リターンメッセージ"
                    },
                    "RefreshAfterFinish": true,
                    "CheckDataValidation": false
                  },
                  {
                    "$type": "Forguncy.Model.ConditionCommand, ServerDesignerCommon",
                    "ConditionAndCommandPairList": [
                      {
                        "Condition": {
                          "$type": "Forguncy.Model.IfCondition, ServerDesignerCommon",
                          "param": {
                            "$type": "Forguncy.Model.IfConditionPageElementParam, ServerDesignerCommon",
                            "cellLocations": [
                              {
                                "SerializeProperty": "='74995f23fcce42ecba69efcc8a3414e'!リターンコード"
                              }
                            ]
                          },
                          "value": "0",
                          "compareType": 1
                        },
                        "CommandList": [
                          {
                            "$type": "Forguncy.Model.ShowMessageCommand, ServerDesignerCommon",
                            "MessageFormula": {
                              "$type": "Forguncy.Model.FormulaReferObject, ServerDesignerCommon",
                              "SerializeProperty": "='74995f23fcce42ecba69efcc8a3414e'!リターンメッセージ"
                            }
                          }
                        ],
                        "ID": "c113de99-b162-4ca9-beac-17b76229ce9f"
                      }
                    ]
                  }
                ],
                "ID": "22f4862a-a49a-4791-b744-cc1672ac080e"
              }
            ]
          }
        ],
        "ToolTip": "ファイルを削除します",
        "TemplateKey": "リスト用",
        "ImagePath": "Application/037_delete_2.svg",
        "BuiltIn": true,
        "Color": "Background 1 -35",
        "UseCellForeColor": true
      }
    },
    "1,2": {
      "TemplateCellSource": "ファイル属性名"
    },
    "1,11": {
      "TemplateCellSource": "ファイルサイズ"
    },
    "1,17": {
      "TemplateCellSource": "ファイル作成日時"
    },
    "1,24": {
      "TemplateCellSource": "アップロードユーザー名"
    },
    "1,48": {
      "TemplateCellSource": "添付ID"
    },
    "1,51": {
      "TemplateCellSource": "添付コメント数"
    }
  },
  "StyleDatas": {
    "Styles": [
      {
        "FontFamily": 0
      },
      {
        "FontFamily": 0,
        "FontSize": 14.666666666666666,
        "FontWeight": 1,
        "Foreground": 2,
        "TextIndent": 4,
        "Underline": true,
        "ShrinkToFit": true
      },
      {
        "FontFamily": 0,
        "FontSize": 12.0,
        "HorizontalAlignment": 3
      },
      {
        "FontFamily": 0,
        "FontSize": 12.0,
        "HorizontalAlignment": 4
      },
      {
        "FontFamily": 0,
        "FontSize": 12.0,
        "Foreground": null
      },
      {
        "FontFamily": 0,
        "FontSize": 12.0
      },
      {
        "BorderBottom": 0
      },
      {
        "FontSize": 14.666666666666666,
        "Foreground": 6,
        "TextIndent": 4,
        "BorderBottom": 0,
        "ShrinkToFit": true
      },
      {
        "BorderBottom": 0,
        "BorderRight": null
      },
      {
        "FontFamily": 0,
        "FontSize": 12.0,
        "Foreground": 7,
        "Formatter": 8,
        "HorizontalAlignment": 9,
        "BorderBottom": 0
      },
      {
        "FontFamily": 0,
        "FontSize": 12.0,
        "BorderBottom": 0
      },
      {
        "FontFamily": 0,
        "FontSize": 12.0,
        "Foreground": 7,
        "Formatter": 10,
        "HorizontalAlignment": 3,
        "BorderBottom": 0
      },
      {
        "FontFamily": 0,
        "FontSize": 12.0,
        "HorizontalAlignment": 3,
        "BorderBottom": 0
      },
      {
        "FontFamily": 0,
        "FontSize": 12.0,
        "HorizontalAlignment": 4,
        "BorderBottom": 0
      },
      {
        "BorderBottom": null
      },
      {
        "Background": 11
      },
      {
        "HorizontalAlignment": 4
      },
      {
        "FontSize": 12.0
      },
      {
        "FontSize": 12.0,
        "HorizontalAlignment": 9
      },
      {
        "FontSize": 12.0,
        "HorizontalAlignment": 4
      },
      {
        "FontSize": 12.0,
        "Foreground": 7,
        "HorizontalAlignment": 4
      },
      {
        "FontSize": 12.0,
        "Foreground": 7
      },
      {
        "FontSize": 12.0,
        "Foreground": 12
      }
    ],
    "Types": {
      "Strs": [
        "Body",
        "Bold",
        "#FF005B47",
        "Left",
        "Center",
        "Background 1 -15",
        "#FF000000",
        "Background 1 -35",
        "#,##0KB",
        "Right",
        "yyyy/mm/dd hh:mm",
        "#FFFFFF00",
        "Text 1 50"
      ],
      "Borders": [
        {
          "Color": 5
        }
      ]
    },
    "CellStyles": {
      "0,0": 0,
      "0,2": 1,
      "0,24": 2,
      "0,25": 3,
      "0,26": 3,
      "0,27": 3,
      "0,28": 3,
      "0,29": 3,
      "0,30": 3,
      "0,31": 2,
      "0,33": 2,
      "0,34": 4,
      "0,37": 4,
      "0,38": 5,
      "0,40": 4,
      "0,41": 5,
      "0,43": 4,
      "0,45": 5,
      "1,0": 6,
      "1,1": 6,
      "1,2": 7,
      "1,3": 6,
      "1,4": 6,
      "1,5": 6,
      "1,6": 6,
      "1,7": 6,
      "1,8": 8,
      "1,9": 6,
      "1,10": 6,
      "1,11": 9,
      "1,12": 10,
      "1,13": 10,
      "1,14": 10,
      "1,15": 10,
      "1,16": 6,
      "1,17": 11,
      "1,18": 6,
      "1,19": 6,
      "1,20": 6,
      "1,21": 6,
      "1,22": 6,
      "1,23": 6,
      "1,24": 12,
      "1,25": 13,
      "1,26": 13,
      "1,27": 13,
      "1,28": 13,
      "1,29": 13,
      "1,30": 13,
      "1,31": 6,
      "1,32": 6,
      "1,33": 12,
      "1,34": 6,
      "1,35": 6,
      "1,36": 6,
      "1,37": 10,
      "1,38": 10,
      "1,39": 6,
      "1,40": 10,
      "1,41": 10,
      "1,42": 6,
      "1,43": 6,
      "1,44": 6,
      "1,45": 10,
      "1,46": 6,
      "1,47": 14,
      "1,48": 15,
      "1,51": 15,
      "1,54": 14,
      "1,55": 14
    },
    "ColStyles": {
      "0": 16,
      "1": 16,
      "2": 17,
      "3": 17,
      "4": 17,
      "5": 17,
      "6": 17,
      "7": 17,
      "8": 17,
      "9": 17,
      "10": 17,
      "11": 17,
      "12": 17,
      "13": 17,
      "14": 17,
      "15": 17,
      "16": 17,
      "17": 17,
      "18": 17,
      "19": 17,
      "20": 17,
      "21": 18,
      "22": 18,
      "23": 18,
      "24": 19,
      "25": 19,
      "26": 19,
      "27": 19,
      "28": 19,
      "29": 19,
      "30": 19,
      "31": 19,
      "32": 19,
      "33": 19,
      "34": 20,
      "35": 20,
      "36": 17,
      "37": 21,
      "38": 21,
      "39": 17,
      "40": 21,
      "41": 21,
      "42": 17,
      "43": 22,
      "44": 22,
      "45": 21,
      "46": 17,
      "47": 17,
      "48": 17,
      "49": 17,
      "50": 17,
      "51": 17,
      "52": 17,
      "53": 17
    },
    "SheetStyle": {
      "FontFamily": 0
    }
  },
  "Spans": [
    "1,2,1,7",
    "0,43,2,2",
    "0,40,2,2",
    "1,11,1,5",
    "0,0,1,2",
    "0,37,2,2",
    "1,24,1,7",
    "0,24,1,7",
    "1,17,1,7",
    "1,48,1,2",
    "0,2,1,21",
    "1,51,1,2",
    "0,34,2,2",
    "0,31,2,2"
  ],
  "PageInfo": {
    "$type": "Forguncy.Model.Pages.TemplatePage, ServerDesignerCommon",
    "ParentPageName": "添付ファイルリスト"
  },
  "PrintInfo": {
    "Margin": {},
    "PaperSize": {}
  }
}//mroo8HjXaram0u2hiQY2tOtoA3zWlwwbbUQlGIPw2liYtZ8o+qDGUGlN0CwySfu8VqQYrrrDJezqoQqo1f9bx+ItwJjHmeDIbLrCTaG5HifHUTG0KRt3J1R06ODRxOxsGvtfspcNyIwGMnT1A1YUKYDLMOCbiPnstwxBuGu14y4zgQTyjphJtNpvEorfBdKHls1ppsqCbOPA9AzvkboIkF/OuijvtrQguuQbI4weC8/4AFvf2f4rT8HojjUeQ+OqC633TkhtE+s/yXuP4NFUifDTtUvJAYa9nAZLEMtPoqtdyX00aXLLpcPfcMjjYy228e6GfDCd/6FhzngBgvua8ia7ocj2aBwyZ/j36BdHObiVHpmG02JT0O0yNnlo87M6sW7V5+ugAcud34Tyl/xmNBUfHhyNd5ciMraPqBgmuW+24j3uX42fhC1tw5QV2t+jjbJyWaJ13NCpfTdHBDxtkC3vcVXepzQLn/TcKToFRm02tfPQzr1tseml/tJL+ILepmGPpIN2CFBWlrp2A0lJwaLCBhuftyR0m2tzlW6AEKOgCeqdcErA30jhqNY0tYJsmogHMqUPF5AyPeT82sU9v8tG7Pr1G28G0h5arJKaIxeN6v/VGFKnzNUF3RTQIfvlspPZ3VsnWGicWFLdeG5bKtCg1TCKC7xa3Qu1x8cKgMHj2Lpek5oeA/0gWFUFBEzEruheo0eSz2sAjlCvZWGGNaPOnEcKKtxCGPkAPDLzP83HCZw2bWF5mXAv1l5JyIRWiTGTdyXdc1X9PDkg+aNBsEPTSppIKkGeEdRiGmujV31XQTOkEhum4OgZZ4mDejoUUjrZxYxReANRijwPn9vyObSbrOht0ykIcZQstycrtriCQsMXxGYQPX4duK7OBLVJgadaRD+CuEsr0rThMkISEA==|920